sbanken/__init__.py
sbanken/account.py
sbanken/auth.py
sbanken/client.py
sbanken/const.py
sbanken/efaktura.py
sbanken/sbanken.py
sbanken/transaction.py
sbanken_api-0.4.1.dist-info/LICENSE
sbanken_api-0.4.1.dist-info/METADATA
sbanken_api-0.4.1.dist-info/WHEEL
sbanken_api-0.4.1.dist-info/top_level.txt
sbanken_api-0.4.1.dist-info/RECORD
