Metadata-Version: 2.1
Name: sbanken-api
Version: 0.4.1
Summary: Easy (async) communication with Sbanken API in python
Home-page: https://github.com/abstrakct/sbanken-python
Author: Rolf Klausen
Author-email: redacted@mail.com
License: UNKNOWN
Download-URL: https://github.com/abstrakct/sbanken-python/archive/v0.4.tar.gz
Platform: UNKNOWN
Classifier: Programming Language :: Python :: 3
Classifier: License :: OSI Approved :: MIT License
Classifier: Operating System :: OS Independent
Classifier: Development Status :: 5 - Production/Stable
Classifier: Intended Audience :: Developers
Classifier: Topic :: Office/Business :: Financial
Requires-Dist: oauthlib
Requires-Dist: requests
Requires-Dist: requests-oauthlib
